readmodule/__init__.py
readmodule/__main__.py
readmodule/server.py
readmodule-0.1.3.dist-info/licenses/LICENSE
readmodule-0.1.3.dist-info/METADATA
readmodule-0.1.3.dist-info/WHEEL
readmodule-0.1.3.dist-info/entry_points.txt
readmodule-0.1.3.dist-info/top_level.txt
readmodule-0.1.3.dist-info/RECORD
