Metadata-Version: 2.4
Name: readmodule
Version: 0.1.3
Summary: MCP Server for reading OpenHarmony module code
Author-email: lwt <liangweitao@openvalley.net>
License:                                  Apache License
Keywords: mcp,openharmony,code-reader
Classifier: Programming Language :: Python :: 3
Classifier: Programming Language :: Python :: 3.10
Classifier: Programming Language :: Python :: 3.11
Classifier: Programming Language :: Python :: 3.12
Classifier: License :: OSI Approved :: Apache Software License
Classifier: Operating System :: OS Independent
Classifier: Topic :: Software Development :: Libraries
Classifier: Framework :: FastAPI
Classifier: Intended Audience :: Developers
Classifier: Development Status :: 4 - Beta
Classifier: Topic :: Utilities
Requires-Python: >=3.10
License-File: LICENSE
Requires-Dist: fastmcp
Requires-Dist: httpx>=0.28.1
Requires-Dist: mcp[cli]>=1.6.0
Dynamic: license-file
